[
  {
    "firstName": "A",
    "lastName": "A",
    "email": "A",
    "phone": "mamsodsdadasd",
    "date": "Thursday, September 26, 2024",
    "startTime": "7:00 AM",
    "endTime": "8:00 AM"
  },
  {
    "firstName": "a",
    "lastName": "a",
    "email": "a",
    "phone": "a",
    "date": "Thursday, September 26, 2024",
    "startTime": "7:00 AM",
    "endTime": "8:00 AM"
  },
  {
    "firstName": "Manoranjan",
    "lastName": "A",
    "email": "manoranjan.0611@gmail.com",
    "phone": "9383334141",
    "date": "Thursday, September 26, 2024",
    "startTime": "7:00 AM",
    "endTime": "8:00 AM"
  }
]